[
    {
        "bridge_id": 1,
        "name": "OmniBridge",
        "type": "lockmint",
        "indexer": "OmniBridge",
        "enabled": true,
        "api_url": null,
        "ui_url": "https://bridge.gnosischain.com/",
        "contracts": [
            {
                "chain_id": 1,
                "address": "0x4C36d2919e407f0Cc2Ee3c993ccF8ac26d9CE64e",
                "version": 1,
                "started_at_block": 9298324
            },
            {
                "chain_id": 100,
                "address": "0x75Df5AF045d91108662D8080fD1FEFAd6aA0bb59",
                "version": 1,
                "started_at_block": 7904954
            }
        ]
    }
]