{
    "counters_order": [
        "average_block_time",
        "completed_txns",
        "last_new_contracts",
        "last_new_verified_contracts",
        "total_accounts",
        "total_addresses",
        "total_blocks",
        "total_contracts",
        "total_native_coin_holders",
        "total_native_coin_transfers",
        "total_tokens",
        "total_txns",
        "op_stack_total_operational_txns",
        "total_operational_txns",
        "total_user_ops",
        "total_account_abstraction_wallets",
        "total_verified_contracts",
        "new_txns_24h",
        "op_stack_new_operational_txns_24h",
        "new_operational_txns_24h",
        "pending_txns_30m",
        "txns_fee_24h",
        "average_txn_fee_24h"
    ],
    "line_chart_categories": [
        {
            "id": "accounts",
            "title": "Accounts",
            "charts_order": [
                "accounts_growth",
                "active_accounts",
                "new_accounts",
                "new_builder_accounts",
                "builder_accounts_growth",
                "active_recurring_accounts_60_days",
                "active_recurring_accounts_90_days",
                "active_recurring_accounts_120_days"
            ]
        },
        {
            "id": "transactions",
            "title": "Transactions",
            "charts_order": [
                "average_txn_fee",
                "new_txns",
                "txns_fee",
                "txns_growth",
                "op_stack_new_operational_txns",
                "op_stack_operational_txns_growth",
                "new_operational_txns",
                "operational_txns_growth",
                "txns_success_rate",
                "new_eip_7702_auths",
                "eip_7702_auths_growth"
            ]
        },
        {
            "id": "blocks",
            "title": "Blocks",
            "charts_order": [
                "average_block_rewards",
                "average_block_size",
                "new_blocks"
            ]
        },
        {
            "id": "tokens",
            "title": "Tokens",
            "charts_order": [
                "native_coin_holders_growth",
                "native_coin_supply",
                "new_native_coin_holders",
                "new_native_coin_transfers"
            ]
        },
        {
            "id": "gas",
            "title": "Gas",
            "charts_order": [
                "average_gas_limit",
                "average_gas_price",
                "gas_used_growth",
                "network_utilization",
                "average_gas_used"
            ]
        },
        {
            "id": "contracts",
            "title": "Contracts",
            "charts_order": [
                "contracts_growth",
                "new_contracts",
                "new_verified_contracts",
                "verified_contracts_growth"
            ]
        },
        {
            "id": "user_ops",
            "title": "User operations",
            "charts_order": [
                "user_ops_growth",
                "new_user_ops",
                "new_account_abstraction_wallets",
                "account_abstraction_wallets_growth",
                "active_account_abstraction_wallets",
                "active_bundlers",
                "active_paymasters"
            ]
        }
    ]
}